realgas/__init__.py
realgas/cp.py
realgas/cp_ig.csv
realgas/critical_constants.csv
realgas/critical_constants.py
realgas/input.py
realgas/partial_molar_properties.py
realgas/thermal_conductivity.csv
realgas/thermal_conductivity.py
realgas/viscosity.csv
realgas/viscosity.py
realgas/eos/__init__.py
realgas/eos/cubic.py
realgas/eos/virial.py
realgas-1.1.2.dist-info/LICENSE
realgas-1.1.2.dist-info/METADATA
realgas-1.1.2.dist-info/WHEEL
realgas-1.1.2.dist-info/top_level.txt
realgas-1.1.2.dist-info/RECORD
